fable_modules/fable_library/__init__.py
fable_modules/fable_library/array.py
fable_modules/fable_library/async_.py
fable_modules/fable_library/async_builder.py
fable_modules/fable_library/big_int.py
fable_modules/fable_library/bit_converter.py
fable_modules/fable_library/boolean.py
fable_modules/fable_library/char.py
fable_modules/fable_library/choice.py
fable_modules/fable_library/date.py
fable_modules/fable_library/date_offset.py
fable_modules/fable_library/decimal.py
fable_modules/fable_library/double.py
fable_modules/fable_library/event.py
fable_modules/fable_library/fsharp_collections.py
fable_modules/fable_library/fsharp_core.py
fable_modules/fable_library/global_.py
fable_modules/fable_library/guid.py
fable_modules/fable_library/int32.py
fable_modules/fable_library/list.py
fable_modules/fable_library/long.py
fable_modules/fable_library/mailbox_processor.py
fable_modules/fable_library/map.py
fable_modules/fable_library/map_util.py
fable_modules/fable_library/mutable_map.py
fable_modules/fable_library/mutable_set.py
fable_modules/fable_library/native.py
fable_modules/fable_library/numeric.py
fable_modules/fable_library/observable.py
fable_modules/fable_library/option.py
fable_modules/fable_library/range.py
fable_modules/fable_library/reflection.py
fable_modules/fable_library/reg_exp.py
fable_modules/fable_library/resize_array.py
fable_modules/fable_library/seq.py
fable_modules/fable_library/seq2.py
fable_modules/fable_library/set.py
fable_modules/fable_library/string.py
fable_modules/fable_library/system_collections_generic.py
fable_modules/fable_library/system_text.py
fable_modules/fable_library/task.py
fable_modules/fable_library/task_builder.py
fable_modules/fable_library/time_span.py
fable_modules/fable_library/timer.py
fable_modules/fable_library/types.py
fable_modules/fable_library/uri.py
fable_modules/fable_library/util.py
architecture_modelling_tomfreeman-0.0.1.dist-info/LICENSE
architecture_modelling_tomfreeman-0.0.1.dist-info/METADATA
architecture_modelling_tomfreeman-0.0.1.dist-info/WHEEL
architecture_modelling_tomfreeman-0.0.1.dist-info/top_level.txt
architecture_modelling_tomfreeman-0.0.1.dist-info/RECORD
