Metadata-Version: 2.1
Name: architecture-modelling-tomfreeman
Version: 0.0.1
Summary: A package to enable modelling systems architectures
Author: Thomas Freeman
License: MIT License        
Project-URL: Homepage, https://github.com/TomFreeman/architecture-modelling
Project-URL: Bug Tracker, https://github.com/TomFreeman/architecture-modelling/issues
Classifier: Programming Language :: Python :: 3
Classifier: License :: OSI Approved :: MIT License
Classifier: Operating System :: OS Independent
Requires-Python: >=3.7
License-File: LICENSE
